setup.cfg
setup.py
proboscis/__init__.py
proboscis/asserts.py
proboscis/case.py
proboscis/check.py
proboscis/core.py
proboscis/decorators.py
proboscis/dependencies.py
proboscis/sorting.py
proboscis.egg-info/PKG-INFO
proboscis.egg-info/SOURCES.txt
proboscis.egg-info/dependency_links.txt
proboscis.egg-info/top_level.txt
proboscis/compatability/__init__.py
proboscis/compatability/exceptions_2_5.py
proboscis/compatability/exceptions_2_6.py
proboscis/compatability/raise_2_x.py
proboscis/compatability/raise_3_x.py