Metadata-Version: 1.0
Name: proboscis
Version: 1.2.5.3
Summary: Extends Nose with certain TestNG like features.
Home-page: https://github.com/rackspace/python-proboscis
Author: Rackspace
Author-email: tim.simpson@rackspace.com
License: Apache
Keywords: nose test testng
Platform: UNKNOWN
Classifier: Development Status :: 5 - Production/Stable
Classifier: Environment :: Console
Classifier: Intended Audience :: Developers
Classifier: Intended Audience :: Information Technology
Classifier: License :: OSI Approved :: Apache Software License
Classifier: Operating System :: OS Independent
Classifier: Programming Language :: Python
